pylog/__init__.py
pylog/control_structures.py
pylog/logic_variables.py
pylog/sequence_options/__init__.py
pylog/sequence_options/linked_list.py
pylog/sequence_options/sequences.py
pylog/sequence_options/super_sequence.py
pylog-1.1.dist-info/METADATA
pylog-1.1.dist-info/WHEEL
pylog-1.1.dist-info/top_level.txt
pylog-1.1.dist-info/RECORD
