Metadata-Version: 2.1
Name: pylog
Version: 1.1
Summary: Python implementation of Prolog features.
Home-page: https://github.com/RussAbbott/pylog
Author: Russ Abbott, Jay Patel
Author-email: Russ.Abbott@gmail.com, imjaypatel12@gmail.com
License: MIT
Keywords: prolog python logic programming
Platform: UNKNOWN
Classifier: Development Status :: 3 - Alpha
Classifier: License :: OSI Approved :: MIT License
Classifier: Programming Language :: Python :: 3.7
Classifier: Topic :: Software Development :: Libraries :: Python Modules
Requires-Python: >=3.7
